Changelog.md
Logo.png
MANIFEST.in
README.md
setup.py
PyEngine_2D.egg-info/PKG-INFO
PyEngine_2D.egg-info/SOURCES.txt
PyEngine_2D.egg-info/dependency_links.txt
PyEngine_2D.egg-info/requires.txt
PyEngine_2D.egg-info/top_level.txt
pyengine/Exceptions.py
pyengine/Window.py
pyengine/World.py
pyengine/__init__.py
pyengine/Components/AnimComponent.py
pyengine/Components/ControlComponent.py
pyengine/Components/LifeComponent.py
pyengine/Components/MoveComponent.py
pyengine/Components/PhysicsComponent.py
pyengine/Components/PositionComponent.py
pyengine/Components/SpriteComponent.py
pyengine/Components/TextComponent.py
pyengine/Components/__init__.py
pyengine/Entities/Entity.py
pyengine/Entities/Tilemap.py
pyengine/Entities/__init__.py
pyengine/Network/Client.py
pyengine/Network/NetworkManager.py
pyengine/Network/Packet.py
pyengine/Network/Server.py
pyengine/Network/__init__.py
pyengine/Systems/CameraSystem.py
pyengine/Systems/EntitySystem.py
pyengine/Systems/MusicSystem.py
pyengine/Systems/SoundSystem.py
pyengine/Systems/UISystem.py
pyengine/Systems/__init__.py
pyengine/Utils/Color.py
pyengine/Utils/Config.py
pyengine/Utils/Font.py
pyengine/Utils/Lang.py
pyengine/Utils/Logger.py
pyengine/Utils/Others.py
pyengine/Utils/Vec2.py
pyengine/Utils/__init__.py
pyengine/Widgets/AnimatedImage.py
pyengine/Widgets/Button.py
pyengine/Widgets/Checkbox.py
pyengine/Widgets/Console.py
pyengine/Widgets/Entry.py
pyengine/Widgets/Image.py
pyengine/Widgets/Label.py
pyengine/Widgets/MultilineLabel.py
pyengine/Widgets/ProgressBar.py
pyengine/Widgets/Selector.py
pyengine/Widgets/Widget.py
pyengine/Widgets/__init__.py