Metadata-Version: 2.1
Name: PyEngine-2D
Version: 1.6.0
Summary: A lib to create 2D games
Home-page: http://github.com/LavaPower/PyEngine
Author: LavaPower
Author-email: lavapower84@gmail.com
License: UNKNOWN
Platform: UNKNOWN
Classifier: Programming Language :: Python
Classifier: Development Status :: 5 - Production/Stable
Classifier: License :: OSI Approved :: GNU General Public License v3 (GPLv3)
Classifier: Natural Language :: English
Classifier: Operating System :: OS Independent
Classifier: Programming Language :: Python :: 3.7
Classifier: Topic :: Software Development :: Libraries :: pygame
Classifier: Intended Audience :: Developers
